AUTHORS.rst
CONTRIBUTING.rst
HISTORY.rst
LICENSE
MANIFEST.in
README.rst
setup.cfg
setup.py
django_envelope_save.egg-info/PKG-INFO
django_envelope_save.egg-info/SOURCES.txt
django_envelope_save.egg-info/dependency_links.txt
django_envelope_save.egg-info/not-zip-safe
django_envelope_save.egg-info/requires.txt
django_envelope_save.egg-info/top_level.txt
envelope_save/__init__.py
envelope_save/admin.py
envelope_save/apps.py
envelope_save/models.py
envelope_save/urls.py
envelope_save/views.py
envelope_save/migrations/0001_initial.py
envelope_save/migrations/__init__.py
envelope_save/static/css/django_envelope_save.css
envelope_save/static/js/django_envelope_save.js
envelope_save/templates/django_envelope_save/base.html