Metadata-Version: 1.1
Name: django-envelope-save
Version: 0.2.0
Summary: Simple app which listens to signals from django-envelope and saves contact form submissions to the database.
Home-page: https://github.com/LaunchlabAU/django-envelope-save
Author: Dave Pretty
Author-email: david@launchlab.com.au
License: MIT
Keywords: django-envelope-save
Platform: UNKNOWN
Classifier: Development Status :: 3 - Alpha
Classifier: Framework :: Django
Classifier: Framework :: Django :: 1.8
Classifier: Framework :: Django :: 1.9
Classifier: Framework :: Django :: 1.10
Classifier: Intended Audience :: Developers
Classifier: License :: OSI Approved :: BSD License
Classifier: Natural Language :: English
Classifier: Programming Language :: Python :: 2
Classifier: Programming Language :: Python :: 2.7
Classifier: Programming Language :: Python :: 3
Classifier: Programming Language :: Python :: 3.2
Classifier: Programming Language :: Python :: 3.3
Classifier: Programming Language :: Python :: 3.4
Classifier: Programming Language :: Python :: 3.5
